{
 "custom_fields": [
  {
   "_assign": null,
   "_comments": null,
   "_liked_by": null,
   "_user_tags": null,
   "allow_in_quick_entry": 0,
   "allow_on_submit": 0,
   "bold": 0,
   "collapsible": 0,
   "collapsible_depends_on": null,
   "columns": 0,
   "creation": "2019-04-24 07:12:48.060919",
   "default": null,
   "depends_on": null,
   "description": null,
   "docstatus": 0,
   "dt": "Customer",
   "fetch_from": null,
   "fetch_if_empty": 0,
   "fieldname": "trade_name",
   "fieldtype": "Link",
   "hidden": 0,
   "hide_border": 0,
   "hide_days": 0,
   "hide_seconds": 0,
   "idx": 6,
   "ignore_user_permissions": 0,
   "ignore_xss_filter": 0,
   "in_global_search": 0,
   "in_list_view": 0,
   "in_preview": 0,
   "in_standard_filter": 0,
   "insert_after": "naming_series",
   "label": "Trade Name",
   "length": 0,
   "mandatory_depends_on": null,
   "modified": "2019-04-24 07:12:48.060919",
   "modified_by": "Administrator",
   "name": "Customer-trade_name",
   "no_copy": 0,
   "non_negative": 0,
   "options": "Trade Name",
   "owner": "Administrator",
   "parent": null,
   "parentfield": null,
   "parenttype": null,
   "permlevel": 0,
   "precision": "",
   "print_hide": 0,
   "print_hide_if_no_value": 0,
   "print_width": null,
   "read_only": 0,
   "read_only_depends_on": null,
   "report_hide": 0,
   "reqd": 0,
   "search_index": 0,
   "translatable": 0,
   "unique": 0,
   "width": null
  },
  {
   "_assign": null,
   "_comments": null,
   "_liked_by": null,
   "_user_tags": null,
   "allow_in_quick_entry": 0,
   "allow_on_submit": 0,
   "bold": 0,
   "collapsible": 0,
   "collapsible_depends_on": null,
   "columns": 0,
   "creation": "2019-04-24 07:12:49.054575",
   "default": "1",
   "depends_on": null,
   "description": null,
   "docstatus": 0,
   "dt": "Customer",
   "fetch_from": null,
   "fetch_if_empty": 0,
   "fieldname": "back_order_accepted",
   "fieldtype": "Check",
   "hidden": 0,
   "hide_border": 0,
   "hide_days": 0,
   "hide_seconds": 0,
   "idx": 18,
   "ignore_user_permissions": 0,
   "ignore_xss_filter": 0,
   "in_global_search": 0,
   "in_list_view": 0,
   "in_preview": 0,
   "in_standard_filter": 0,
   "insert_after": "opportunity_name",
   "label": "Back Order Accepted",
   "length": 0,
   "mandatory_depends_on": "",
   "modified": "2019-04-24 07:12:49.054575",
   "modified_by": "Administrator",
   "name": "Customer-back_order_accepted",
   "no_copy": 0,
   "non_negative": 0,
   "options": null,
   "owner": "Administrator",
   "parent": null,
   "parentfield": null,
   "parenttype": null,
   "permlevel": 0,
   "precision": "",
   "print_hide": 0,
   "print_hide_if_no_value": 0,
   "print_width": null,
   "read_only": 0,
   "read_only_depends_on": null,
   "report_hide": 0,
   "reqd": 1,
   "search_index": 0,
   "translatable": 0,
   "unique": 0,
   "width": null
  },
  {
   "_assign": null,
   "_comments": null,
   "_liked_by": null,
   "_user_tags": null,
   "allow_in_quick_entry": 0,
   "allow_on_submit": 0,
   "bold": 0,
   "collapsible": 0,
   "collapsible_depends_on": null,
   "columns": 0,
   "creation": "2019-04-24 07:12:49.998377",
   "default": null,
   "depends_on": null,
   "description": null,
   "docstatus": 0,
   "dt": "Customer",
   "fetch_from": null,
   "fetch_if_empty": 0,
   "fieldname": "activity_code",
   "fieldtype": "Data",
   "hidden": 0,
   "hide_border": 0,
   "hide_days": 0,
   "hide_seconds": 0,
   "idx": 27,
   "ignore_user_permissions": 0,
   "ignore_xss_filter": 0,
   "in_global_search": 0,
   "in_list_view": 0,
   "in_preview": 0,
   "in_standard_filter": 0,
   "insert_after": "art_customer_registration_no",
   "label": "Activity Code",
   "length": 0,
   "mandatory_depends_on": null,
   "modified": "2019-04-24 07:12:49.998377",
   "modified_by": "Administrator",
   "name": "Customer-activity_code",
   "no_copy": 0,
   "non_negative": 0,
   "options": "",
   "owner": "Administrator",
   "parent": null,
   "parentfield": null,
   "parenttype": null,
   "permlevel": 0,
   "precision": "",
   "print_hide": 0,
   "print_hide_if_no_value": 0,
   "print_width": null,
   "read_only": 0,
   "read_only_depends_on": null,
   "report_hide": 0,
   "reqd": 0,
   "search_index": 0,
   "translatable": 0,
   "unique": 0,
   "width": null
  },
  {
   "_assign": null,
   "_comments": null,
   "_liked_by": null,
   "_user_tags": null,
   "allow_in_quick_entry": 0,
   "allow_on_submit": 0,
   "bold": 0,
   "collapsible": 0,
   "collapsible_depends_on": null,
   "columns": 0,
   "creation": "2019-04-24 07:12:55.283295",
   "default": null,
   "depends_on": null,
   "description": null,
   "docstatus": 0,
   "dt": "Customer",
   "fetch_from": null,
   "fetch_if_empty": 0,
   "fieldname": "art_customer_sales_person",
   "fieldtype": "Section Break",
   "hidden": 0,
   "hide_border": 0,
   "hide_days": 0,
   "hide_seconds": 0,
   "idx": 72,
   "ignore_user_permissions": 0,
   "ignore_xss_filter": 0,
   "in_global_search": 0,
   "in_list_view": 0,
   "in_preview": 0,
   "in_standard_filter": 0,
   "insert_after": "default_commission_rate",
   "label": "Art Customer Sales Person",
   "length": 0,
   "mandatory_depends_on": null,
   "modified": "2019-04-24 07:12:55.283295",
   "modified_by": "Administrator",
   "name": "Customer-art_customer_sales_person",
   "no_copy": 0,
   "non_negative": 0,
   "options": null,
   "owner": "Administrator",
   "parent": null,
   "parentfield": null,
   "parenttype": null,
   "permlevel": 0,
   "precision": "",
   "print_hide": 0,
   "print_hide_if_no_value": 0,
   "print_width": null,
   "read_only": 0,
   "read_only_depends_on": null,
   "report_hide": 0,
   "reqd": 0,
   "search_index": 0,
   "translatable": 0,
   "unique": 0,
   "width": null
  },
  {
   "_assign": null,
   "_comments": null,
   "_liked_by": null,
   "_user_tags": null,
   "allow_in_quick_entry": 0,
   "allow_on_submit": 0,
   "bold": 0,
   "collapsible": 0,
   "collapsible_depends_on": null,
   "columns": 0,
   "creation": "2019-04-24 07:12:56.838790",
   "default": null,
   "depends_on": null,
   "description": null,
   "docstatus": 0,
   "dt": "Customer",
   "fetch_from": null,
   "fetch_if_empty": 0,
   "fieldname": "customer_sales_person",
   "fieldtype": "Table",
   "hidden": 0,
   "hide_border": 0,
   "hide_days": 0,
   "hide_seconds": 0,
   "idx": 73,
   "ignore_user_permissions": 0,
   "ignore_xss_filter": 0,
   "in_global_search": 0,
   "in_list_view": 0,
   "in_preview": 0,
   "in_standard_filter": 0,
   "insert_after": "art_customer_sales_person",
   "label": "Customer Sales Person",
   "length": 0,
   "mandatory_depends_on": null,
   "modified": "2019-04-24 07:12:56.838790",
   "modified_by": "Administrator",
   "name": "Customer-customer_sales_person",
   "no_copy": 0,
   "non_negative": 0,
   "options": "Customer Sales Person",
   "owner": "Administrator",
   "parent": null,
   "parentfield": null,
   "parenttype": null,
   "permlevel": 0,
   "precision": "",
   "print_hide": 0,
   "print_hide_if_no_value": 0,
   "print_width": null,
   "read_only": 0,
   "read_only_depends_on": null,
   "report_hide": 0,
   "reqd": 0,
   "search_index": 0,
   "translatable": 0,
   "unique": 0,
   "width": null
  },
  {
   "_assign": null,
   "_comments": null,
   "_liked_by": null,
   "_user_tags": null,
   "allow_in_quick_entry": 0,
   "allow_on_submit": 0,
   "bold": 0,
   "collapsible": 0,
   "collapsible_depends_on": null,
   "columns": 0,
   "creation": "2019-05-17 18:11:06.097033",
   "default": null,
   "depends_on": null,
   "description": null,
   "docstatus": 0,
   "dt": "Customer",
   "fetch_from": null,
   "fetch_if_empty": 0,
   "fieldname": "woocommerce_id",
   "fieldtype": "Data",
   "hidden": 1,
   "hide_border": 0,
   "hide_days": 0,
   "hide_seconds": 0,
   "idx": 3,
   "ignore_user_permissions": 0,
   "ignore_xss_filter": 0,
   "in_global_search": 0,
   "in_list_view": 0,
   "in_preview": 0,
   "in_standard_filter": 0,
   "insert_after": "woocommerce_email",
   "label": "woocommerce_id",
   "length": 0,
   "mandatory_depends_on": null,
   "modified": "2019-05-17 18:11:06.097033",
   "modified_by": "Administrator",
   "name": "Customer-woocommerce_id",
   "no_copy": 0,
   "non_negative": 0,
   "options": null,
   "owner": "Administrator",
   "parent": null,
   "parentfield": null,
   "parenttype": null,
   "permlevel": 0,
   "precision": "",
   "print_hide": 0,
   "print_hide_if_no_value": 0,
   "print_width": null,
   "read_only": 1,
   "read_only_depends_on": null,
   "report_hide": 0,
   "reqd": 0,
   "search_index": 0,
   "translatable": 1,
   "unique": 0,
   "width": null
  },
  {
   "_assign": null,
   "_comments": null,
   "_liked_by": null,
   "_user_tags": null,
   "allow_in_quick_entry": 0,
   "allow_on_submit": 0,
   "bold": 0,
   "collapsible": 0,
   "collapsible_depends_on": null,
   "columns": 0,
   "creation": "2019-05-17 18:11:06.594949",
   "default": null,
   "depends_on": null,
   "description": null,
   "docstatus": 0,
   "dt": "Customer",
   "fetch_from": null,
   "fetch_if_empty": 0,
   "fieldname": "woocommerce_check",
   "fieldtype": "Check",
   "hidden": 1,
   "hide_border": 0,
   "hide_days": 0,
   "hide_seconds": 0,
   "idx": 1,
   "ignore_user_permissions": 0,
   "ignore_xss_filter": 0,
   "in_global_search": 0,
   "in_list_view": 0,
   "in_preview": 0,
   "in_standard_filter": 0,
   "insert_after": null,
   "label": "woocommerce_check",
   "length": 0,
   "mandatory_depends_on": null,
   "modified": "2019-05-17 18:11:06.594949",
   "modified_by": "Administrator",
   "name": "Customer-woocommerce_check",
   "no_copy": 0,
   "non_negative": 0,
   "options": null,
   "owner": "Administrator",
   "parent": null,
   "parentfield": null,
   "parenttype": null,
   "permlevel": 0,
   "precision": "",
   "print_hide": 0,
   "print_hide_if_no_value": 0,
   "print_width": null,
   "read_only": 1,
   "read_only_depends_on": null,
   "report_hide": 0,
   "reqd": 0,
   "search_index": 0,
   "translatable": 0,
   "unique": 0,
   "width": null
  },
  {
   "_assign": null,
   "_comments": null,
   "_liked_by": null,
   "_user_tags": null,
   "allow_in_quick_entry": 0,
   "allow_on_submit": 0,
   "bold": 0,
   "collapsible": 0,
   "collapsible_depends_on": null,
   "columns": 0,
   "creation": "2019-05-17 18:11:09.209385",
   "default": null,
   "depends_on": null,
   "description": null,
   "docstatus": 0,
   "dt": "Customer",
   "fetch_from": null,
   "fetch_if_empty": 0,
   "fieldname": "woocommerce_email",
   "fieldtype": "Data",
   "hidden": 1,
   "hide_border": 0,
   "hide_days": 0,
   "hide_seconds": 0,
   "idx": 2,
   "ignore_user_permissions": 0,
   "ignore_xss_filter": 0,
   "in_global_search": 0,
   "in_list_view": 0,
   "in_preview": 0,
   "in_standard_filter": 0,
   "insert_after": "woocommerce_check",
   "label": "woocommerce_email",
   "length": 0,
   "mandatory_depends_on": null,
   "modified": "2019-05-17 18:11:09.209385",
   "modified_by": "Administrator",
   "name": "Customer-woocommerce_email",
   "no_copy": 0,
   "non_negative": 0,
   "options": null,
   "owner": "Administrator",
   "parent": null,
   "parentfield": null,
   "parenttype": null,
   "permlevel": 0,
   "precision": "",
   "print_hide": 0,
   "print_hide_if_no_value": 0,
   "print_width": null,
   "read_only": 1,
   "read_only_depends_on": null,
   "report_hide": 0,
   "reqd": 0,
   "search_index": 0,
   "translatable": 1,
   "unique": 0,
   "width": null
  },
  {
   "_assign": null,
   "_comments": null,
   "_liked_by": null,
   "_user_tags": null,
   "allow_in_quick_entry": 0,
   "allow_on_submit": 0,
   "bold": 0,
   "collapsible": 0,
   "collapsible_depends_on": null,
   "columns": 0,
   "creation": "2019-05-27 12:28:10.730243",
   "default": null,
   "depends_on": null,
   "description": null,
   "docstatus": 0,
   "dt": "Customer",
   "fetch_from": null,
   "fetch_if_empty": 0,
   "fieldname": "art_customer_registration_no",
   "fieldtype": "Data",
   "hidden": 0,
   "hide_border": 0,
   "hide_days": 0,
   "hide_seconds": 0,
   "idx": 26,
   "ignore_user_permissions": 0,
   "ignore_xss_filter": 0,
   "in_global_search": 0,
   "in_list_view": 0,
   "in_preview": 0,
   "in_standard_filter": 0,
   "insert_after": "tax_id",
   "label": "Registration No",
   "length": 0,
   "mandatory_depends_on": null,
   "modified": "2019-05-27 12:28:10.730243",
   "modified_by": "Administrator",
   "name": "Customer-art_customer_registration_no",
   "no_copy": 0,
   "non_negative": 0,
   "options": null,
   "owner": "Administrator",
   "parent": null,
   "parentfield": null,
   "parenttype": null,
   "permlevel": 0,
   "precision": "",
   "print_hide": 0,
   "print_hide_if_no_value": 0,
   "print_width": null,
   "read_only": 0,
   "read_only_depends_on": null,
   "report_hide": 0,
   "reqd": 0,
   "search_index": 0,
   "translatable": 1,
   "unique": 0,
   "width": null
  },
  {
   "_assign": null,
   "_comments": null,
   "_liked_by": null,
   "_user_tags": null,
   "allow_in_quick_entry": 0,
   "allow_on_submit": 0,
   "bold": 0,
   "collapsible": 0,
   "collapsible_depends_on": null,
   "columns": 0,
   "creation": "2019-08-22 06:51:28.762533",
   "default": null,
   "depends_on": "",
   "description": null,
   "docstatus": 0,
   "dt": "Customer",
   "fetch_from": "lead_name.source",
   "fetch_if_empty": 0,
   "fieldname": "lead_source_art",
   "fieldtype": "Link",
   "hidden": 0,
   "hide_border": 0,
   "hide_days": 0,
   "hide_seconds": 0,
   "idx": 16,
   "ignore_user_permissions": 0,
   "ignore_xss_filter": 0,
   "in_global_search": 0,
   "in_list_view": 0,
   "in_preview": 0,
   "in_standard_filter": 0,
   "insert_after": "lead_name",
   "label": "Lead Source",
   "length": 0,
   "mandatory_depends_on": null,
   "modified": "2019-08-22 06:51:28.762533",
   "modified_by": "Administrator",
   "name": "Customer-lead_source_art",
   "no_copy": 0,
   "non_negative": 0,
   "options": "Lead Source",
   "owner": "Administrator",
   "parent": null,
   "parentfield": null,
   "parenttype": null,
   "permlevel": 0,
   "precision": "",
   "print_hide": 0,
   "print_hide_if_no_value": 0,
   "print_width": null,
   "read_only": 0,
   "read_only_depends_on": null,
   "report_hide": 0,
   "reqd": 0,
   "search_index": 0,
   "translatable": 0,
   "unique": 0,
   "width": null
  },
  {
   "_assign": null,
   "_comments": null,
   "_liked_by": null,
   "_user_tags": null,
   "allow_in_quick_entry": 0,
   "allow_on_submit": 0,
   "bold": 0,
   "collapsible": 1,
   "collapsible_depends_on": null,
   "columns": 0,
   "creation": "2019-08-22 07:19:52.110719",
   "default": null,
   "depends_on": null,
   "description": null,
   "docstatus": 0,
   "dt": "Customer",
   "fetch_from": null,
   "fetch_if_empty": 0,
   "fieldname": "customer_target_section_art",
   "fieldtype": "Section Break",
   "hidden": 0,
   "hide_border": 0,
   "hide_days": 0,
   "hide_seconds": 0,
   "idx": 77,
   "ignore_user_permissions": 0,
   "ignore_xss_filter": 0,
   "in_global_search": 0,
   "in_list_view": 0,
   "in_preview": 0,
   "in_standard_filter": 0,
   "insert_after": "customer_pos_id",
   "label": "Customer Target",
   "length": 0,
   "mandatory_depends_on": null,
   "modified": "2019-08-22 07:19:52.110719",
   "modified_by": "Administrator",
   "name": "Customer-customer_target_section_art",
   "no_copy": 0,
   "non_negative": 0,
   "options": null,
   "owner": "Administrator",
   "parent": null,
   "parentfield": null,
   "parenttype": null,
   "permlevel": 0,
   "precision": "",
   "print_hide": 0,
   "print_hide_if_no_value": 0,
   "print_width": null,
   "read_only": 0,
   "read_only_depends_on": null,
   "report_hide": 0,
   "reqd": 0,
   "search_index": 0,
   "translatable": 0,
   "unique": 0,
   "width": null
  },
  {
   "_assign": null,
   "_comments": null,
   "_liked_by": null,
   "_user_tags": null,
   "allow_in_quick_entry": 0,
   "allow_on_submit": 0,
   "bold": 0,
   "collapsible": 0,
   "collapsible_depends_on": null,
   "columns": 0,
   "creation": "2019-08-22 07:19:52.563861",
   "default": null,
   "depends_on": null,
   "description": "ensure : (a) no boundary overlapping values  (b) continuous range for a given year",
   "docstatus": 0,
   "dt": "Customer",
   "fetch_from": null,
   "fetch_if_empty": 0,
   "fieldname": "customer_target_art",
   "fieldtype": "Table",
   "hidden": 0,
   "hide_border": 0,
   "hide_days": 0,
   "hide_seconds": 0,
   "idx": 78,
   "ignore_user_permissions": 0,
   "ignore_xss_filter": 0,
   "in_global_search": 0,
   "in_list_view": 0,
   "in_preview": 0,
   "in_standard_filter": 0,
   "insert_after": "customer_target_section_art",
   "label": "Customer Goal Year-wise",
   "length": 0,
   "mandatory_depends_on": null,
   "modified": "2019-08-22 07:19:52.563861",
   "modified_by": "Administrator",
   "name": "Customer-customer_target_art",
   "no_copy": 0,
   "non_negative": 0,
   "options": "Customer Target Art",
   "owner": "Administrator",
   "parent": null,
   "parentfield": null,
   "parenttype": null,
   "permlevel": 0,
   "precision": "",
   "print_hide": 0,
   "print_hide_if_no_value": 0,
   "print_width": null,
   "read_only": 0,
   "read_only_depends_on": null,
   "report_hide": 0,
   "reqd": 0,
   "search_index": 0,
   "translatable": 0,
   "unique": 0,
   "width": null
  },
  {
   "_assign": null,
   "_comments": null,
   "_liked_by": null,
   "_user_tags": null,
   "allow_in_quick_entry": 0,
   "allow_on_submit": 0,
   "bold": 0,
   "collapsible": 0,
   "collapsible_depends_on": null,
   "columns": 0,
   "creation": "2021-08-19 07:20:26.693526",
   "default": null,
   "depends_on": null,
   "description": null,
   "docstatus": 0,
   "dt": "Customer",
   "fetch_from": null,
   "fetch_if_empty": 0,
   "fieldname": "incoterm",
   "fieldtype": "Select",
   "hidden": 0,
   "hide_border": 0,
   "hide_days": 0,
   "hide_seconds": 0,
   "idx": 14,
   "ignore_user_permissions": 0,
   "ignore_xss_filter": 0,
   "in_global_search": 0,
   "in_list_view": 0,
   "in_preview": 0,
   "in_standard_filter": 0,
   "insert_after": "default_bank_account",
   "label": "Incoterm",
   "length": 0,
   "mandatory_depends_on": null,
   "modified": "2021-06-13 17:13:48.709352",
   "modified_by": "Administrator",
   "name": "Customer-incoterm",
   "no_copy": 0,
   "non_negative": 0,
   "options": "EXW ex-works\nFCA free carrier\nFAS free alongside ship\nFOB free on board\nCFR cost and freight\nCIF (COST insurance and freight)\nCPT \u2013 Carriage Paid to (duty paid)\nCIP Carriage and Insurance paid to\nDAF (Delivered at Frontier)\nDES (Delivered ex-ship)\nDEQ (Delivered EX quay)\nDDU (delivered duty unpaid)\nDDP (delivered duty paid)",
   "owner": "Administrator",
   "parent": null,
   "parentfield": null,
   "parenttype": null,
   "permlevel": 0,
   "precision": "",
   "print_hide": 0,
   "print_hide_if_no_value": 0,
   "print_width": null,
   "read_only": 0,
   "read_only_depends_on": null,
   "report_hide": 0,
   "reqd": 0,
   "search_index": 0,
   "translatable": 1,
   "unique": 0,
   "width": null
  },
  {
   "_assign": null,
   "_comments": null,
   "_liked_by": null,
   "_user_tags": null,
   "allow_in_quick_entry": 0,
   "allow_on_submit": 0,
   "bold": 0,
   "collapsible": 0,
   "collapsible_depends_on": null,
   "columns": 0,
   "creation": "2022-01-21 06:22:18.671198",
   "default": null,
   "depends_on": null,
   "description": null,
   "docstatus": 0,
   "dt": "Customer",
   "fetch_from": null,
   "fetch_if_empty": 0,
   "fieldname": "default_mode_of_payment_art",
   "fieldtype": "Link",
   "hidden": 0,
   "hide_border": 0,
   "hide_days": 0,
   "hide_seconds": 0,
   "idx": 28,
   "ignore_user_permissions": 0,
   "ignore_xss_filter": 0,
   "in_global_search": 0,
   "in_list_view": 0,
   "in_preview": 0,
   "in_standard_filter": 0,
   "insert_after": "activity_code",
   "label": "Default Mode Of Payment",
   "length": 0,
   "mandatory_depends_on": null,
   "modified": "2022-01-21 06:22:18.671198",
   "modified_by": "Administrator",
   "name": "Customer-default_mode_of_payment_art",
   "no_copy": 0,
   "non_negative": 0,
   "options": "Mode of Payment",
   "owner": "Administrator",
   "parent": null,
   "parentfield": null,
   "parenttype": null,
   "permlevel": 0,
   "precision": "",
   "print_hide": 0,
   "print_hide_if_no_value": 0,
   "print_width": null,
   "read_only": 0,
   "read_only_depends_on": null,
   "report_hide": 0,
   "reqd": 0,
   "search_index": 0,
   "translatable": 0,
   "unique": 0,
   "width": null
  },
  {
   "_assign": null,
   "_comments": null,
   "_liked_by": null,
   "_user_tags": null,
   "allow_in_quick_entry": 0,
   "allow_on_submit": 0,
   "bold": 0,
   "collapsible": 0,
   "collapsible_depends_on": null,
   "columns": 0,
   "creation": "2022-07-06 08:38:45.888645",
   "default": null,
   "depends_on": null,
   "description": null,
   "docstatus": 0,
   "dt": "Customer",
   "fetch_from": null,
   "fetch_if_empty": 0,
   "fieldname": "minimum_order_amount_cf",
   "fieldtype": "Float",
   "hidden": 0,
   "hide_border": 0,
   "hide_days": 0,
   "hide_seconds": 0,
   "idx": 56,
   "ignore_user_permissions": 0,
   "ignore_xss_filter": 0,
   "in_global_search": 0,
   "in_list_view": 0,
   "in_preview": 0,
   "in_standard_filter": 0,
   "insert_after": "credit_limit_section",
   "label": "Minimum Order Amount",
   "length": 0,
   "mandatory_depends_on": null,
   "modified": "2022-07-06 08:38:45.888645",
   "modified_by": "Administrator",
   "name": "Customer-minimum_order_amount_cf",
   "no_copy": 0,
   "non_negative": 0,
   "options": null,
   "owner": "Administrator",
   "parent": null,
   "parentfield": null,
   "parenttype": null,
   "permlevel": 0,
   "precision": "",
   "print_hide": 0,
   "print_hide_if_no_value": 0,
   "print_width": null,
   "read_only": 0,
   "read_only_depends_on": null,
   "report_hide": 0,
   "reqd": 0,
   "search_index": 0,
   "translatable": 0,
   "unique": 0,
   "width": null
  },
  {
   "_assign": null,
   "_comments": null,
   "_liked_by": null,
   "_user_tags": null,
   "allow_in_quick_entry": 0,
   "allow_on_submit": 0,
   "bold": 0,
   "collapsible": 0,
   "collapsible_depends_on": null,
   "columns": 0,
   "creation": "2022-08-29 07:46:47.606671",
   "default": "0",
   "depends_on": null,
   "description": null,
   "docstatus": 0,
   "dt": "Customer",
   "fetch_from": null,
   "fetch_if_empty": 0,
   "fieldname": "has_volume_price_cf",
   "fieldtype": "Check",
   "hidden": 0,
   "hide_border": 0,
   "hide_days": 0,
   "hide_seconds": 0,
   "idx": 19,
   "ignore_user_permissions": 0,
   "ignore_xss_filter": 0,
   "in_global_search": 0,
   "in_list_view": 0,
   "in_preview": 0,
   "in_standard_filter": 0,
   "insert_after": "back_order_accepted",
   "label": "Has volume price ?",
   "length": 0,
   "mandatory_depends_on": null,
   "modified": "2022-08-29 07:46:47.606671",
   "modified_by": "Administrator",
   "name": "Customer-has_volume_price_cf",
   "no_copy": 0,
   "non_negative": 0,
   "options": null,
   "owner": "Administrator",
   "parent": null,
   "parentfield": null,
   "parenttype": null,
   "permlevel": 0,
   "precision": "",
   "print_hide": 0,
   "print_hide_if_no_value": 0,
   "print_width": null,
   "read_only": 0,
   "read_only_depends_on": null,
   "report_hide": 0,
   "reqd": 0,
   "search_index": 0,
   "translatable": 0,
   "unique": 0,
   "width": null
  }
 ],
 "custom_perms": [],
 "doctype": "Customer",
 "property_setters": [
  {
   "_assign": null,
   "_comments": null,
   "_liked_by": null,
   "_user_tags": null,
   "creation": "2022-08-31 08:11:11.839489",
   "default_value": null,
   "doc_type": "Customer",
   "docstatus": 0,
   "doctype_or_field": "DocType",
   "field_name": null,
   "idx": 0,
   "modified": "2022-08-31 08:11:11.839489",
   "modified_by": "Administrator",
   "name": "Customer-main-links_order",
   "owner": "Administrator",
   "parent": null,
   "parentfield": null,
   "parenttype": null,
   "property": "links_order",
   "property_type": "Small Text",
   "row_name": null,
   "value": "[\"fe32298ab9\", \"edb9f6e621\"]"
  },
  {
   "_assign": null,
   "_comments": null,
   "_liked_by": null,
   "_user_tags": null,
   "creation": "2022-08-31 08:11:11.674990",
   "default_value": null,
   "doc_type": "Customer",
   "docstatus": 0,
   "doctype_or_field": "DocField",
   "field_name": "is_frozen",
   "idx": 0,
   "modified": "2022-08-31 08:11:11.674990",
   "modified_by": "Administrator",
   "name": "Customer-is_frozen-hidden",
   "owner": "Administrator",
   "parent": null,
   "parentfield": null,
   "parenttype": null,
   "property": "hidden",
   "property_type": "Check",
   "row_name": null,
   "value": "1"
  },
  {
   "_assign": null,
   "_comments": null,
   "_liked_by": null,
   "_user_tags": null,
   "creation": "2022-08-31 08:11:11.517043",
   "default_value": null,
   "doc_type": "Customer",
   "docstatus": 0,
   "doctype_or_field": "DocField",
   "field_name": "industry",
   "idx": 0,
   "modified": "2022-08-31 08:11:11.517043",
   "modified_by": "Administrator",
   "name": "Customer-industry-hidden",
   "owner": "Administrator",
   "parent": null,
   "parentfield": null,
   "parenttype": null,
   "property": "hidden",
   "property_type": "Check",
   "row_name": null,
   "value": "1"
  },
  {
   "_assign": null,
   "_comments": null,
   "_liked_by": null,
   "_user_tags": null,
   "creation": "2022-08-31 08:11:11.287535",
   "default_value": null,
   "doc_type": "Customer",
   "docstatus": 0,
   "doctype_or_field": "DocField",
   "field_name": "market_segment",
   "idx": 0,
   "modified": "2022-08-31 08:11:11.287535",
   "modified_by": "Administrator",
   "name": "Customer-market_segment-hidden",
   "owner": "Administrator",
   "parent": null,
   "parentfield": null,
   "parenttype": null,
   "property": "hidden",
   "property_type": "Check",
   "row_name": null,
   "value": "1"
  },
  {
   "_assign": null,
   "_comments": null,
   "_liked_by": null,
   "_user_tags": null,
   "creation": "2022-08-31 08:07:42.629618",
   "default_value": null,
   "doc_type": "Customer",
   "docstatus": 0,
   "doctype_or_field": "DocField",
   "field_name": "is_internal_customer",
   "idx": 0,
   "modified": "2022-08-31 08:07:42.629618",
   "modified_by": "Administrator",
   "name": "Customer-is_internal_customer-hidden",
   "owner": "Administrator",
   "parent": null,
   "parentfield": null,
   "parenttype": null,
   "property": "hidden",
   "property_type": "Check",
   "row_name": null,
   "value": "1"
  },
  {
   "_assign": null,
   "_comments": null,
   "_liked_by": null,
   "_user_tags": null,
   "creation": "2022-08-31 08:07:42.452116",
   "default_value": null,
   "doc_type": "Customer",
   "docstatus": 0,
   "doctype_or_field": "DocField",
   "field_name": "dn_required",
   "idx": 0,
   "modified": "2022-08-31 08:07:42.452116",
   "modified_by": "Administrator",
   "name": "Customer-dn_required-hidden",
   "owner": "Administrator",
   "parent": null,
   "parentfield": null,
   "parenttype": null,
   "property": "hidden",
   "property_type": "Check",
   "row_name": null,
   "value": "1"
  },
  {
   "_assign": null,
   "_comments": null,
   "_liked_by": null,
   "_user_tags": null,
   "creation": "2022-08-31 08:07:41.938323",
   "default_value": null,
   "doc_type": "Customer",
   "docstatus": 0,
   "doctype_or_field": "DocField",
   "field_name": "so_required",
   "idx": 0,
   "modified": "2022-08-31 08:07:41.938323",
   "modified_by": "Administrator",
   "name": "Customer-so_required-hidden",
   "owner": "Administrator",
   "parent": null,
   "parentfield": null,
   "parenttype": null,
   "property": "hidden",
   "property_type": "Check",
   "row_name": null,
   "value": "1"
  },
  {
   "_assign": null,
   "_comments": null,
   "_liked_by": null,
   "_user_tags": null,
   "creation": "2022-08-22 10:46:42.975649",
   "default_value": null,
   "doc_type": "Customer",
   "docstatus": 0,
   "doctype_or_field": "DocField",
   "field_name": "opportunity_name",
   "idx": 0,
   "modified": "2022-08-22 10:46:42.975649",
   "modified_by": "Administrator",
   "name": "Customer-opportunity_name-hidden",
   "owner": "Administrator",
   "parent": null,
   "parentfield": null,
   "parenttype": null,
   "property": "hidden",
   "property_type": "Check",
   "row_name": null,
   "value": "1"
  },
  {
   "_assign": null,
   "_comments": null,
   "_liked_by": null,
   "_user_tags": null,
   "creation": "2022-08-08 07:20:15.332747",
   "default_value": null,
   "doc_type": "Customer",
   "docstatus": 0,
   "doctype_or_field": "DocField",
   "field_name": "payment_terms",
   "idx": 0,
   "modified": "2022-08-08 07:20:15.332747",
   "modified_by": "Administrator",
   "name": "Customer-payment_terms-fetch_from",
   "owner": "Administrator",
   "parent": null,
   "parentfield": null,
   "parenttype": null,
   "property": "fetch_from",
   "property_type": "Small Text",
   "row_name": null,
   "value": ""
  },
  {
   "_assign": null,
   "_comments": null,
   "_liked_by": null,
   "_user_tags": null,
   "creation": "2022-07-06 08:35:12.107198",
   "default_value": null,
   "doc_type": "Customer",
   "docstatus": 0,
   "doctype_or_field": "DocField",
   "field_name": "default_price_list",
   "idx": 0,
   "modified": "2022-07-06 08:35:12.107198",
   "modified_by": "Administrator",
   "name": "Customer-default_price_list-fetch_from",
   "owner": "Administrator",
   "parent": null,
   "parentfield": null,
   "parenttype": null,
   "property": "fetch_from",
   "property_type": "Small Text",
   "row_name": null,
   "value": ""
  },
  {
   "_assign": null,
   "_comments": null,
   "_liked_by": null,
   "_user_tags": null,
   "creation": "2022-07-05 11:27:40.677956",
   "default_value": null,
   "doc_type": "Customer",
   "docstatus": 0,
   "doctype_or_field": "DocField",
   "field_name": "sales_team_section",
   "idx": 0,
   "modified": "2022-07-05 11:27:40.677956",
   "modified_by": "Administrator",
   "name": "Customer-sales_team_section-hidden",
   "owner": "Administrator",
   "parent": null,
   "parentfield": null,
   "parenttype": null,
   "property": "hidden",
   "property_type": "Check",
   "row_name": null,
   "value": "1"
  },
  {
   "_assign": null,
   "_comments": null,
   "_liked_by": null,
   "_user_tags": null,
   "creation": "2022-07-04 08:45:30.933602",
   "default_value": null,
   "doc_type": "Customer",
   "docstatus": 0,
   "doctype_or_field": "DocField",
   "field_name": "sales_team_section_break",
   "idx": 0,
   "modified": "2022-07-04 08:45:30.933602",
   "modified_by": "Administrator",
   "name": "Customer-sales_team_section_break-hidden",
   "owner": "Administrator",
   "parent": null,
   "parentfield": null,
   "parenttype": null,
   "property": "hidden",
   "property_type": "Check",
   "row_name": null,
   "value": "1"
  },
  {
   "_assign": null,
   "_comments": null,
   "_liked_by": null,
   "_user_tags": null,
   "creation": "2022-07-04 08:44:26.073154",
   "default_value": null,
   "doc_type": "Customer",
   "docstatus": 0,
   "doctype_or_field": "DocField",
   "field_name": "column_break_38",
   "idx": 0,
   "modified": "2022-07-04 08:44:26.073154",
   "modified_by": "Administrator",
   "name": "Customer-column_break_38-hidden",
   "owner": "Administrator",
   "parent": null,
   "parentfield": null,
   "parenttype": null,
   "property": "hidden",
   "property_type": "Check",
   "row_name": null,
   "value": "1"
  },
  {
   "_assign": null,
   "_comments": null,
   "_liked_by": null,
   "_user_tags": null,
   "creation": "2022-07-04 08:43:27.058982",
   "default_value": null,
   "doc_type": "Customer",
   "docstatus": 0,
   "doctype_or_field": "DocField",
   "field_name": "default_bank_account",
   "idx": 0,
   "modified": "2022-07-04 08:43:27.058982",
   "modified_by": "Administrator",
   "name": "Customer-default_bank_account-hidden",
   "owner": "Administrator",
   "parent": null,
   "parentfield": null,
   "parenttype": null,
   "property": "hidden",
   "property_type": "Check",
   "row_name": null,
   "value": "1"
  },
  {
   "_assign": null,
   "_comments": null,
   "_liked_by": null,
   "_user_tags": null,
   "creation": "2022-07-04 08:34:10.224159",
   "default_value": null,
   "doc_type": "Customer",
   "docstatus": 0,
   "doctype_or_field": "DocField",
   "field_name": "tax_withholding_category",
   "idx": 0,
   "modified": "2022-07-04 08:34:10.224159",
   "modified_by": "Administrator",
   "name": "Customer-tax_withholding_category-hidden",
   "owner": "Administrator",
   "parent": null,
   "parentfield": null,
   "parenttype": null,
   "property": "hidden",
   "property_type": "Check",
   "row_name": null,
   "value": "1"
  },
  {
   "_assign": null,
   "_comments": null,
   "_liked_by": null,
   "_user_tags": null,
   "creation": "2022-07-04 08:33:27.323546",
   "default_value": null,
   "doc_type": "Customer",
   "docstatus": 0,
   "doctype_or_field": "DocField",
   "field_name": "pan",
   "idx": 0,
   "modified": "2022-07-04 08:33:27.323546",
   "modified_by": "Administrator",
   "name": "Customer-pan-hidden",
   "owner": "Administrator",
   "parent": null,
   "parentfield": null,
   "parenttype": null,
   "property": "hidden",
   "property_type": "Check",
   "row_name": null,
   "value": "1"
  },
  {
   "_assign": null,
   "_comments": null,
   "_liked_by": null,
   "_user_tags": null,
   "creation": "2019-09-28 10:17:05.054351",
   "default_value": null,
   "doc_type": "Customer",
   "docstatus": 0,
   "doctype_or_field": "DocField",
   "field_name": "naming_series",
   "idx": 0,
   "modified": "2021-08-19 17:17:05.054351",
   "modified_by": "Administrator",
   "name": "Customer-naming_series-options",
   "owner": "Administrator",
   "parent": null,
   "parentfield": null,
   "parenttype": null,
   "property": "options",
   "property_type": "Text",
   "row_name": null,
   "value": "CUST-.YYYY.-"
  }
 ],
 "sync_on_migrate": 1
}